annoworkcli/__init__.py
annoworkcli/__main__.py
annoworkcli/account/__init__.py
annoworkcli/account/list_external_linkage_info.py
annoworkcli/account/put_external_linkage_info.py
annoworkcli/account/subcommand.py
annoworkcli/actual_working_time/__init__.py
annoworkcli/actual_working_time/delete_actual_working_time.py
annoworkcli/actual_working_time/list_actual_working_hours_daily.py
annoworkcli/actual_working_time/list_actual_working_hours_daily_groupby_tag.py
annoworkcli/actual_working_time/list_actual_working_time.py
annoworkcli/actual_working_time/list_actual_working_time_weekly.py
annoworkcli/actual_working_time/subcommand.py
annoworkcli/annofab/__init__.py
annoworkcli/annofab/list_assigned_hours.py
annoworkcli/annofab/list_job_with_annofab_project.py
annoworkcli/annofab/list_working_hours.py
annoworkcli/annofab/put_account_external_linkage_info.py
annoworkcli/annofab/put_job_from_annofab_project.py
annoworkcli/annofab/reshape_working_hours.py
annoworkcli/annofab/subcommand.py
annoworkcli/annofab/utils.py
annoworkcli/annofab/visualize_statistics.py
annoworkcli/common/__init__.py
annoworkcli/common/annofab.py
annoworkcli/common/cli.py
annoworkcli/common/exeptions.py
annoworkcli/common/job.py
annoworkcli/common/type_util.py
annoworkcli/common/utils.py
annoworkcli/common/workspace_tag.py
annoworkcli/data/logging.yaml
annoworkcli/expected_working_time/__init__.py
annoworkcli/expected_working_time/delete_expected_working_time.py
annoworkcli/expected_working_time/list_expected_working_time.py
annoworkcli/expected_working_time/list_expected_working_time_groupby_tag.py
annoworkcli/expected_working_time/list_expected_working_time_weekly.py
annoworkcli/expected_working_time/subcommand.py
annoworkcli/job/__init__.py
annoworkcli/job/change_job_properties.py
annoworkcli/job/delete_job.py
annoworkcli/job/list_job.py
annoworkcli/job/subcommand.py
annoworkcli/my/__init__.py
annoworkcli/my/get_my_account.py
annoworkcli/my/list_my_workspace_member.py
annoworkcli/my/subcommand.py
annoworkcli-3.12.0.dist-info/METADATA
annoworkcli-3.12.0.dist-info/WHEEL
annoworkcli-3.12.0.dist-info/entry_points.txt
annoworkcli-3.12.0.dist-info/RECORD
