Metadata-Version: 2.4
Name: annoworkcli
Version: 3.12.0
Summary: AnnoworkのCLI(Command Line Interface)
Project-URL: Repository, https://github.com/kurusugawa-computer/annowork-cli
Author: Kurusugawa Computer Inc.
License-Expression: MIT
Keywords: annowork,cli
Classifier: Development Status :: 4 - Beta
Classifier: Environment :: Console
Classifier: Intended Audience :: Developers
Classifier: Operating System :: OS Independent
Classifier: Topic :: Utilities
Requires-Python: >=3.10
Requires-Dist: annofabapi<2,>=1
Requires-Dist: annofabcli>=1.90
Requires-Dist: annoworkapi<4,>=3.2.1
Requires-Dist: isodate
Requires-Dist: more-itertools
Requires-Dist: pandas
Requires-Dist: pyyaml
